{
    "produtos": [
        {
            "id": 1,
            "img": "../../assets/pizza.jpg",
            "restaurante": "Hangar",
            "produto": "Pizza",
            "descricao": "Pizza de Calabresa",
            "preco": 5.00
        },
        {
            "id": 2,
            "img": "../../assets/pastel.webp",
            "restaurante": "Hangar",
            "produto": "Pastel",
            "descricao": "Pastel de Frango",
            "preco": 4.00
        },
        {
            "id": 3,
            "img": "../../assets/cafe.jpg",
            "restaurante": "Hangar",
            "produto": "Café",
            "descricao": "Café Preto com Açúcar",
            "preco": 3.00
        },
        {
            "id": 4,
            "img": "../../assets/pizza.jpg",
            "restaurante": "Da Tia",
            "produto": "Pizza",
            "descricao": "Pizza de Calabresa",
            "preco": 5.00
        },
        {
            "id": 5,
            "img": "../../assets/pastel.webp",
            "restaurante": "Da Tia",
            "produto": "Pastel",
            "descricao": "Pastel de Frango",
            "preco": 4.00
        },
        {
            "id": 6,
            "img": "../../assets/cafe.jpg",
            "restaurante": "Da Tia",
            "produto": "Café",
            "descricao": "Café Preto com Açúcar",
            "preco": 3.00
        }
    ],
    "cartoes": [
        {
            "id": 1,
            "numeroCartao": "1234 5678 9012 3456",
            "id_usuario": 1
        },
        {
            "id": 2,
            "numeroCartao": "1234 5678 9012 3456",
            "id_usuario": 1
        },
        {
            "id": 3,
            "numeroCartao": "1234 5678 9012 3456",
            "id_usuario": 2
        }
    ]
}